pycupid-0.1.7.dist-info/WHEEL
pycupid-0.1.7.dist-info/metadata.json
pycupid-0.1.7.dist-info/top_level.txt
pycupid-0.1.7.dist-info/RECORD
pycupid-0.1.7.dist-info/METADATA
pycupid-0.1.7.dist-info/DESCRIPTION.rst
pycupid/pycupid.so
pycupid/__init__.py
pycupid/star/lib/libcnf.so.0
pycupid/star/lib/libpda.so
pycupid/star/lib/libstarutil.so.0
pycupid/star/lib/libstarmem.so.0
pycupid/star/lib/libchr.so.0
pycupid/star/lib/libary.so.0
pycupid/star/lib/libems.so.0.0.0
pycupid/star/lib/libast_grf_2.0.so.0
pycupid/star/lib/libhds.so.0
pycupid/star/lib/libemsf.so
pycupid/star/lib/libstarutil.so.0.0.0
pycupid/star/lib/libhdsf.so
pycupid/star/lib/libast_pal.so.0.0.0
pycupid/star/lib/libast_grf_5.6.so
pycupid/star/lib/libemsf.so.0.0.0
pycupid/star/lib/libast.so.0.0.0
pycupid/star/lib/libhds.so.0.0.0
pycupid/star/lib/libndf.so.0.0.0
pycupid/star/lib/libhdsf.so.0
pycupid/star/lib/libast_grf_2.0.so
pycupid/star/lib/libgfortran-ed201abd.so.3.0.0
pycupid/star/lib/libast_grf_3.2.so.0.0.0
pycupid/star/lib/libstarmem.so.0.0.0
pycupid/star/lib/libary.so
pycupid/star/lib/libchr.so
pycupid/star/lib/libast.so.0
pycupid/star/lib/libpsx.so.0.0.0
pycupid/star/lib/libast_ems.so.0
pycupid/star/lib/libpsx.so.0
pycupid/star/lib/libast_ems.so.0.0.0
pycupid/star/lib/libast_grf_3.2.so
pycupid/star/lib/libcnf.so.0.0.0
pycupid/star/lib/libast_grf_5.6.so.0.0.0
pycupid/star/lib/libast_grf3d.so
pycupid/star/lib/libprm.so
pycupid/star/lib/libast_grf3d.so.0
pycupid/star/lib/libstarmem.so
pycupid/star/lib/libpsx.so
pycupid/star/lib/libprm_a.so.0.0.0
pycupid/star/lib/libhds.so
pycupid/star/lib/libems.so.0
pycupid/star/lib/libast.so
pycupid/star/lib/libast_err.so.0
pycupid/star/lib/libndf.so.0
pycupid/star/lib/libpda.so.0
pycupid/star/lib/libprm_a.so
pycupid/star/lib/libndf.so
pycupid/star/lib/libems.so
pycupid/star/lib/libast_grf_2.0.so.0.0.0
pycupid/star/lib/libast_grf3d.so.0.0.0
pycupid/star/lib/libcnf.so
pycupid/star/lib/liberr_standalone.so.0.0.0
pycupid/star/lib/libast_pal.so
pycupid/star/lib/libast_err.so.0.0.0
pycupid/star/lib/libprm.so.0
pycupid/star/lib/libprm.so.0.0.0
pycupid/star/lib/libhdsf.so.0.0.0
pycupid/star/lib/libast_grf_5.6.so.0
