Metadata-Version: 2.0
Name: pycupid
Version: 0.1.7
Summary: Python wrappers for Starlink's CUPID package
Home-page: https://github.com/ChileanVirtualObservatory/pycupid
Author: LIRAE TEAM
Author-email: consultas@lirae.cl
License: UNKNOWN
Platform: UNKNOWN
Requires-Dist: numpy (>=1.11.2)
